.gitignore
README.md
setup.py
tests/transliterationtest.py
transliteration/__init__.py
transliteration/cmudict.0.7a_SPHINX_40
transliteration/cmudict.py
transliteration/cmumapping.py
transliteration/core.py
transliteration/indic_en.py
transliteration.egg-info/PKG-INFO
transliteration.egg-info/SOURCES.txt
transliteration.egg-info/dependency_links.txt
transliteration.egg-info/not-zip-safe
transliteration.egg-info/requires.txt
transliteration.egg-info/top_level.txt
transliteration/templates/transliteration.html