Metadata-Version: 1.0
Name: transliteration
Version: 0.4.1
Summary: Indian Language Transliteration Library
Home-page: http://silpa.org.in/Transliterate
Author: Santhosh Thottingal
Author-email: santhosh.thottingal@gmail.com
License: LGPL 3.0
Platform: UNKNOWN
